gammarers/aws_sns_slack_message_lambda_subscription/__init__.py
gammarers/aws_sns_slack_message_lambda_subscription/py.typed
gammarers/aws_sns_slack_message_lambda_subscription/_jsii/__init__.py
gammarers/aws_sns_slack_message_lambda_subscription/_jsii/aws-sns-slack-message-lambda-subscription@1.0.27.jsii.tgz
gammarers_aws_sns_slack_message_lambda_subscription-1.0.27.dist-info/LICENSE
gammarers_aws_sns_slack_message_lambda_subscription-1.0.27.dist-info/METADATA
gammarers_aws_sns_slack_message_lambda_subscription-1.0.27.dist-info/WHEEL
gammarers_aws_sns_slack_message_lambda_subscription-1.0.27.dist-info/top_level.txt
gammarers_aws_sns_slack_message_lambda_subscription-1.0.27.dist-info/RECORD
